pidalu_core/__init__.py
pidalu_core/admin/__init__.py
pidalu_core/admin/mixins.py
pidalu_core/middleware/__init__.py
pidalu_core/middleware/requests.py
pidalu_core/models/__init__.py
pidalu_core/models/audit.py
pidalu_core/models/generics.py
pidalu_core/models/slug.py
pidalu_core/models/softdelete.py
pidalu_core/models/tracker.py
pidalu_core/models/uuid.py
pidalu_core/serializers/__init__.py
pidalu_core/serializers/dynamic_serializer.py
pidalu_core-0.1.3.dist-info/LICENSE
pidalu_core-0.1.3.dist-info/METADATA
pidalu_core-0.1.3.dist-info/WHEEL
pidalu_core-0.1.3.dist-info/RECORD
