Metadata-Version: 2.3
Name: pidalu-core
Version: 0.1.3
Summary: Pidalu Tech - Resusable core models, serializers and middlewares
License: MIT
Author: Pidalu Tech
Requires-Python: >=3.12,<4.0
Classifier: License :: OSI Approved :: MIT License
Classifier: Programming Language :: Python :: 3
Classifier: Programming Language :: Python :: 3.12
Classifier: Programming Language :: Python :: 3.13
Requires-Dist: django (>=5.2.1,<6.0.0)
Requires-Dist: djangorestframework (>=3.16.0,<4.0.0)
